<?xml version="1.0" encoding="UTF-8"?><operatorModel xmlns="http://www.ibm.com/xmlns/prod/streams/spl/operator" xmlns:cmn="http://www.ibm.com/xmlns/prod/streams/spl/common" xmlns:xsi="http://www.w3.org/2001/XMLSchema-instance" xsi:schemaLocation="http://www.ibm.com/xmlns/prod/streams/spl/operator operatorModel.xsd">
  <!--DO NOT EDIT THIS FILE - it is machine generated-->
  <javaOperatorModel>
    <!--Generated from com.ibm.streamsx.speech2text.speechprocessing.callcenter.wavgen.SpeechFileSink in impl/java/bin/com/ibm/streamsx/speech2text/speechprocessing/callcenter/wavgen/SpeechFileSink$StreamsModel.class at Fri Jun 23 09:39:36 EDT 2017-->
    <context>
      <description/>
      <metrics/>
      <executionSettings>
        <className>com.ibm.streamsx.speech2text.speechprocessing.callcenter.wavgen.SpeechFileSink</className>
      </executionSettings>
      <libraryDependencies>
        <library>
          <cmn:description>Operator class library</cmn:description>
          <cmn:managedLibrary>
            <cmn:libPath>../../impl/java/bin</cmn:libPath>
            <cmn:libPath>../../impl/java/lib/*</cmn:libPath>
          </cmn:managedLibrary>
        </library>
      </libraryDependencies>
    </context>
    <parameters>
      <parameter>
        <name>callTimeout</name>
        <description>Seconds to wait before closing a call file</description>
        <optional>true</optional>
        <type>int32</type>
        <cardinality>1</cardinality>
      </parameter>
      <parameter>
        <name>moveToDirectory</name>
        <description>Directory where call files will be moved to once call is completed (and call file is closed)</description>
        <optional>false</optional>
        <type>rstring</type>
        <cardinality>1</cardinality>
      </parameter>
      <parameter>
        <name>scheduledActionPeriod</name>
        <description>Scheduled action period</description>
        <optional>true</optional>
        <type>float64</type>
        <cardinality>1</cardinality>
      </parameter>
      <parameter>
        <name>writeToDirectory</name>
        <description>Directory where call files will be written to</description>
        <optional>false</optional>
        <type>rstring</type>
        <cardinality>1</cardinality>
      </parameter>
    </parameters>
    <inputPorts>
      <inputPortSet>
        <description>Speech data port</description>
        <windowingDescription/>
        <windowingMode>NonWindowed</windowingMode>
        <windowPunctuationInputMode>Oblivious</windowPunctuationInputMode>
        <controlPort>false</controlPort>
        <cardinality>1</cardinality>
        <optional>false</optional>
      </inputPortSet>
    </inputPorts>
    <outputPorts/>
  </javaOperatorModel>
</operatorModel>